MANIFEST.in
README.txt
setup.py
CLMsgr/__init__.py
CLMsgr/api.py
CLMsgr/cli.py
CLMsgr/install.py
CLMsgr.egg-info/PKG-INFO
CLMsgr.egg-info/SOURCES.txt
CLMsgr.egg-info/dependency_links.txt
CLMsgr.egg-info/entry_points.txt
CLMsgr.egg-info/requires.txt
CLMsgr.egg-info/top_level.txt
CLMsgr/chs/Mandriller.py
CLMsgr/chs/__init__.py
CLMsgr/core/__init__.py
CLMsgr/core/accounts.py
CLMsgr/core/channel.py
CLMsgr/core/channels.py
CLMsgr/core/io.py
CLMsgr/core/messages.py
CLMsgr/core/serl.py