Metadata-Version: 1.1
Name: CLMsgr
Version: 0.0.0-pre-alpha-build-3
Summary: A Python Core for Command Line Messaging, with extensibility and modularity
Home-page: https://github.com/GochoMugo/CLMsgr
Author: Gocho Mugo I
Author-email: gochomugo.developer@gmail.com
License: MIT
Download-URL: https://github.com/GochoMugo/CLMsgr/zipball/master
Keywords: commands,messaging,core,cli
Platform: UNKNOWN
Classifier: Development Status :: 2 - Pre-Alpha
Classifier: Environment :: Console
Classifier: Intended Audience :: Developers
Classifier: Intended Audience :: End Users/Desktop
Classifier: Intended Audience :: System Administrators
Classifier: Intended Audience :: Telecommunications Industry
Classifier: License :: OSI Approved
Classifier: License :: OSI Approved :: MIT License
Classifier: Natural Language :: English
Classifier: Operating System :: POSIX
Classifier: Operating System :: POSIX :: Linux
Classifier: Programming Language :: Python
Classifier: Programming Language :: Python :: 2
Classifier: Programming Language :: Python :: 2.7
